lazy_logging/__init__.py
lazy_logging/configure_django_logging.py
lazy_logging/log_colorlog_formatter.py
lazy_logging/log_json_formatter.py
lazy_logging/logger_factory.py
tests/__init__.py
tests/test_dummy.py
lazy_logging-0.0.6.dist-info/LICENSE
lazy_logging-0.0.6.dist-info/METADATA
lazy_logging-0.0.6.dist-info/WHEEL
lazy_logging-0.0.6.dist-info/top_level.txt
lazy_logging-0.0.6.dist-info/RECORD
