Metadata-Version: 2.1
Name: lazy-logging
Version: 0.0.6
Summary: UNKNOWN
Home-page: https://github.com/djeer/lazy_logging
Author: djer
Author-email: djer@github.com
License: UNKNOWN
Platform: UNKNOWN
Classifier: Programming Language :: Python :: 3
Classifier: License :: OSI Approved :: MIT License
Classifier: Operating System :: OS Independent
Requires-Dist: six
